MANIFEST.in
README.md
setup.py
docs/source/imgs/kpm_dos.png
docs/source/imgs/stdog.png
stdog/__init__.py
stdog.egg-info/PKG-INFO
stdog.egg-info/SOURCES.txt
stdog.egg-info/dependency_links.txt
stdog.egg-info/requires.txt
stdog.egg-info/top_level.txt
stdog/dynamics/__init__.py
stdog/dynamics/kuramoto/__init__.py
stdog/dynamics/kuramoto/cuheuns.py
stdog/dynamics/kuramoto/heuns.py
stdog/dynamics/kuramoto/tfops/__init__.py
stdog/dynamics/kuramoto/tfops/heuns.py
stdog/dynamics/kuramoto/tfops/misc.py
stdog/spectra/__init__.py
stdog/spectra/dos.py
stdog/spectra/trace_function.py
stdog/utils/__init__.py
stdog/utils/misc.py
stdog/utils/tfops/__init__.py
stdog/utils/tfops/misc.py