Metadata-Version: 2.1
Name: stdog
Version: 1.0.4
Summary: Structure and Dynamics on Graphs
Home-page: https://github.com/stdogpkg/stdog
Author: Bruno Messias; Thomas K. Peron
Author-email: messias.physics@gmail.com
License: MIT
Download-URL: https://github.com/stdogpkg/stdog/archive/v1.0.4.tar.gz
Keywords: gpu,science,complex-networks,graphs,dynamics,tensorflow,kuramoto
Platform: UNKNOWN
Classifier: Development Status :: 4 - Beta
Classifier: License :: OSI Approved :: MIT License
Classifier: Intended Audience :: Science/Research
Classifier: Programming Language :: Python :: 3
Classifier: Topic :: Scientific/Engineering :: Physics
Classifier: Topic :: Scientific/Engineering :: Mathematics
Classifier: Topic :: Scientific/Engineering :: Information Analysis
